ColorText/ColorText.py
ColorText/__init__.py
Python_ColorText-1.1.3.dist-info/LICENSE
Python_ColorText-1.1.3.dist-info/METADATA
Python_ColorText-1.1.3.dist-info/WHEEL
Python_ColorText-1.1.3.dist-info/top_level.txt
Python_ColorText-1.1.3.dist-info/RECORD
