Metadata-Version: 2.1
Name: Python-ColorText
Version: 1.1.3
Summary: Color Strings in Python easily
Home-page: https://github.com/Sebastian-byte/ColorText
Author: Sebastian Montoya
Author-email: sebastianmontoya209@gmail.com
License: GPL v3
Platform: UNKNOWN
Classifier: Programming Language :: Python :: 3
Classifier: License :: OSI Approved :: GNU General Public License v3 or later (GPLv3+)
Classifier: Operating System :: OS Independent
Requires-Python: >=3.4
Requires-Dist: colorama
